django_medicio_ds/__init__.py
django_medicio_ds/admin.py
django_medicio_ds/apps.py
django_medicio_ds/forms.py
django_medicio_ds/models.py
django_medicio_ds/tests.py
django_medicio_ds/urls.py
django_medicio_ds/views.py
django_medicio_ds/migrations/__init__.py
django_medicio_ds/static/mediciods/css/style.css
django_medicio_ds/static/mediciods/js/main.js
django_medicio_ds/static/mediciods/scss/_footer.scss
django_medicio_ds/static/mediciods/scss/_general.scss
django_medicio_ds/static/mediciods/scss/_header.scss
django_medicio_ds/static/mediciods/scss/_hero.scss
django_medicio_ds/static/mediciods/scss/_nav.scss
django_medicio_ds/static/mediciods/scss/_sections.scss
django_medicio_ds/static/mediciods/scss/_variables.scss
django_medicio_ds/static/mediciods/scss/style.scss
django_medicio_ds/static/mediciods/vendor/animate.css/animate.compat.css
django_medicio_ds/static/mediciods/vendor/animate.css/animate.css
django_medicio_ds/static/mediciods/vendor/animate.css/animate.min.css
django_medicio_ds/static/mediciods/vendor/aos/aos.cjs.js
django_medicio_ds/static/mediciods/vendor/aos/aos.css
django_medicio_ds/static/mediciods/vendor/aos/aos.esm.js
django_medicio_ds/static/mediciods/vendor/aos/aos.js
django_medicio_ds/static/mediciods/vendor/aos/aos.js.map
django_medicio_ds/static/mediciods/vendor/bootstrap/css/bootstrap-grid.css
django_medicio_ds/static/mediciods/vendor/bootstrap/css/bootstrap-grid.css.map
django_medicio_ds/static/mediciods/vendor/bootstrap/css/bootstrap-grid.min.css
django_medicio_ds/static/mediciods/vendor/bootstrap/css/bootstrap-grid.min.css.map
django_medicio_ds/static/mediciods/vendor/bootstrap/css/bootstrap-grid.rtl.css
django_medicio_ds/static/mediciods/vendor/bootstrap/css/bootstrap-grid.rtl.css.map
django_medicio_ds/static/mediciods/vendor/bootstrap/css/bootstrap-grid.rtl.min.css
django_medicio_ds/static/mediciods/vendor/bootstrap/css/bootstrap-grid.rtl.min.css.map
django_medicio_ds/static/mediciods/vendor/bootstrap/css/bootstrap-reboot.css
django_medicio_ds-3.1.0.dist-info/LICENSE
django_medicio_ds-3.1.0.dist-info/WHEEL
django_medicio_ds-3.1.0.dist-info/METADATA
django_medicio_ds-3.1.0.dist-info/RECORD
